pygit2/_pygit2.pyi
pygit2/blame.py
pygit2/settings.py
pygit2/index.py
pygit2/repository.py
pygit2/submodule.py
pygit2/errors.py
pygit2/packbuilder.py
pygit2/__init__.py
pygit2/callbacks.py
pygit2/_build.py
pygit2/config.py
pygit2/_pygit2.pypy38-pp73-x86_64-linux-gnu.so
pygit2/credentials.py
pygit2/remote.py
pygit2/utils.py
pygit2/_run.py
pygit2/_libgit2.pypy38-pp73-x86_64-linux-gnu.so
pygit2/ffi.py
pygit2/refspec.py
pygit2/decl/diff.h
pygit2/decl/clone.h
pygit2/decl/index.h
pygit2/decl/errors.h
pygit2/decl/stash.h
pygit2/decl/repository.h
pygit2/decl/indexer.h
pygit2/decl/config.h
pygit2/decl/callbacks.h
pygit2/decl/submodule.h
pygit2/decl/blame.h
pygit2/decl/types.h
pygit2/decl/pack.h
pygit2/decl/proxy.h
pygit2/decl/transport.h
pygit2/decl/revert.h
pygit2/decl/strarray.h
pygit2/decl/attr.h
pygit2/decl/oid.h
pygit2/decl/checkout.h
pygit2/decl/graph.h
pygit2/decl/commit.h
pygit2/decl/describe.h
pygit2/decl/merge.h
pygit2/decl/refspec.h
pygit2/decl/buffer.h
pygit2/decl/common.h
pygit2/decl/net.h
pygit2/decl/remote.h
pygit2_noteable-1.11.1.dist-info/top_level.txt
pygit2_noteable-1.11.1.dist-info/RECORD
pygit2_noteable-1.11.1.dist-info/WHEEL
pygit2_noteable-1.11.1.dist-info/AUTHORS.rst
pygit2_noteable-1.11.1.dist-info/METADATA
pygit2_noteable-1.11.1.dist-info/COPYING
pygit2_noteable.libs/libpcre-8e472c69.so.3.13.3
pygit2_noteable.libs/libcrypto-bc3b7ca6.so.3
pygit2_noteable.libs/libssh2-8edeca3d.so.1.0.1
pygit2_noteable.libs/libgit2-093accbc.so.1.5.1
pygit2_noteable.libs/libssl-a96b66ca.so.3
