Metadata-Version: 2.1
Name: pygit2-noteable
Version: 1.11.1
Summary: Python bindings for libgit2.
Home-page: https://github.com/noteable-io/pygit2
Maintainer: Noteable (extending from J. David Ibáñez)
Maintainer-email: engineering@noteable.io
License: GPLv2 with linking exception
Project-URL: Documentation, https://www.pygit2.org/
Project-URL: Changelog, https://github.com/libgit2/pygit2/blob/master/CHANGELOG.rst
Project-URL: Funding, https://github.com/sponsors/jdavid
Keywords: git
Classifier: Development Status :: 5 - Production/Stable
Classifier: Intended Audience :: Developers
Classifier: Programming Language :: Python
Classifier: Programming Language :: Python :: 3
Classifier: Programming Language :: Python :: 3.8
Classifier: Programming Language :: Python :: 3.9
Classifier: Programming Language :: Python :: 3.10
Classifier: Programming Language :: Python :: 3.11
Classifier: Programming Language :: Python :: Implementation :: PyPy
Classifier: Programming Language :: Python :: Implementation :: CPython
Classifier: Topic :: Software Development :: Version Control
Requires-Python: >=3.8
License-File: COPYING
License-File: AUTHORS.rst
Requires-Dist: cffi (>=1.9.1)
